sentrypy/__init__.py
sentrypy/models.py
sentrypy/sentry.py
sentrypy/sentryrequesthandler.py
sentrypy/transceiver.py
sentrypy-0.1.8.dist-info/LICENSE
sentrypy-0.1.8.dist-info/METADATA
sentrypy-0.1.8.dist-info/WHEEL
sentrypy-0.1.8.dist-info/top_level.txt
sentrypy-0.1.8.dist-info/RECORD
