Metadata-Version: 2.1
Name: sentrypy
Version: 0.1.8
Summary: The pythonic API wrapper for Sentry.io
Home-page: https://github.com/perfect-operations/sentrypy
Author: Paul Weber
License: LGPL-2.1
Project-URL: Documentation, https://sentrypy.readthedocs.io/en/latest/
Project-URL: Source, https://github.com/perfect-operations/sentrypy
Keywords: sentry api wrapper pythonic
Platform: UNKNOWN
Requires-Python: >=3.8
Requires-Dist: requests
Provides-Extra: dev
Requires-Dist: black ; extra == 'dev'
Requires-Dist: enum-tools[sphinx] ; extra == 'dev'
Requires-Dist: jupyter ; extra == 'dev'
Requires-Dist: pytest ; extra == 'dev'
Requires-Dist: pytest-mock ; extra == 'dev'
Requires-Dist: sphinx ; extra == 'dev'
Requires-Dist: sphinx-rtd-theme ; extra == 'dev'
Requires-Dist: twine ; extra == 'dev'
Requires-Dist: wheel ; extra == 'dev'
